pygubu_designer-0.43.2.dist-info/licenses/AUTHORS
pygubu_designer-0.43.2.dist-info/licenses/LICENSE.md
pygubudesigner/__init__.py
pygubudesigner/__main__.py
pygubudesigner/actions.py
pygubudesigner/bindingseditor.py
pygubudesigner/designerstyles.py
pygubudesigner/i18n.py
pygubudesigner/logpanel.py
pygubudesigner/main.py
pygubudesigner/preferences.py
pygubudesigner/rfilemanager.py
pygubudesigner/uitreeeditor.py
pygubudesigner/widgetdescr.py
pygubudesigner/codegen/__init__.py
pygubudesigner/codegen/codebuilder.py
pygubudesigner/codegen/scriptgenerator.py
pygubudesigner/data/code_templates/app.py.mako
pygubudesigner/data/code_templates/appuser.py.mako
pygubudesigner/data/code_templates/base.py.mako
pygubudesigner/data/code_templates/customstyles.py.mako
pygubudesigner/data/code_templates/fnscript.py.mako
pygubudesigner/data/code_templates/script.py.mako
pygubudesigner/data/code_templates/scriptuser.py.mako
pygubudesigner/data/code_templates/widget.py.mako
pygubudesigner/data/code_templates/widgetbo.py.mako
pygubudesigner/data/code_templates/widgetds.py.mako
pygubudesigner/data/code_templates/widgetuser.py.mako
pygubudesigner/data/iconset/__init__.py
pygubudesigner/data/iconset/dark-ta-adjustments.gif
pygubudesigner/data/iconset/dark-ta-adjustments.png
pygubudesigner/data/iconset/dark-ta-arrow-autofit-height.gif
pygubudesigner/data/iconset/dark-ta-arrow-autofit-height.png
pygubudesigner/data/iconset/dark-ta-arrow-autofit-width.gif
pygubudesigner/data/iconset/dark-ta-arrow-autofit-width.png
pygubudesigner/data/iconset/dark-ta-arrow-move-down-filled.gif
pygubudesigner/data/iconset/dark-ta-arrow-move-down-filled.png
pygubudesigner/data/iconset/dark-ta-arrow-move-left-filled.gif
pygubudesigner/data/iconset/dark-ta-arrow-move-left-filled.png
pygubudesigner/data/iconset/dark-ta-arrow-move-right-filled.gif
pygubudesigner/data/iconset/dark-ta-arrow-move-right-filled.png
pygubudesigner/data/iconset/dark-ta-arrow-move-up-filled.gif
pygubudesigner/data/iconset/dark-ta-arrow-move-up-filled.png
pygubudesigner/data/iconset/dark-ta-arrows-maximize.gif
pygubu_designer-0.43.2.dist-info/METADATA
pygubu_designer-0.43.2.dist-info/WHEEL
pygubu_designer-0.43.2.dist-info/entry_points.txt
pygubu_designer-0.43.2.dist-info/top_level.txt
pygubu_designer-0.43.2.dist-info/RECORD
